{
    "type": "FeatureCollection",
    "features": [
        {
            "type": "Feature",
            "properties": {
                "source_label": "Spanien",
                "start_position": 71,
                "end_position": 78
            },
            "geometry": {
                "type": "Point",
                "coordinates": [
                    "-4",
                    "40"
                ]
            }
        },
        {
            "type": "Feature",
            "properties": {
                "source_label": ":",
                "start_position": 78,
                "end_position": 79
            },
            "geometry": {
                "type": "Point",
                "coordinates": [
                    "-103.72567",
                    "35.17116"
                ]
            }
        }
    ]
}